Workbook

Sheet 1-Financial Model
B2: WaveCare Forecast
D3: 2027 | E3: 2028 | F3: 2029 | G3: 2030 | H3: 2031
B4: Assumptions | C4: Unit | D4: Year 1 | E4: Year 2 | F4: Year 3 | G4: Year 4 | H4: Year 5 | J4: Note
B5: Market Base
B6: Total Addressable Market (Taiwanese market) | C6: # | D6: 1048 | E6: =INT(D6*1.02) -> 1068 | F6: =INT(E6*1.02) -> 1089 | G6: =INT(F6*1.02) -> 1110 | H6: =INT(G6*1.02) -> 1132 | J6: (1) Total Addressable Market (TAM) is expected to increased by 2% each year.
B7: Adoption rate (Taiwanese market) | C7: % | D7: 0.005 | E7: 0.015 | F7: 0.035 | G7: 0.065 | H7: 0.1
B8: Total facilities (Taiwanese market) | C8: # | D8: =INT(D6*D7) -> 5 | E8: =INT(E6*E7) -> 16 | F8: =INT(F6*F7) -> 38 | G8: =INT(G6*G7) -> 72 | H8: =INT(H6*H7) -> 113
B9: Total facilities (Korean pilot) | C9: # | D9: 0 | E9: 0 | F9: 5 | G9: 15 | H9: 25
B10: Total facilities (Japanese pilot) | C10: # | D10: 0 | E10: 0 | F10: 0 | G10: 5 | H10: 10
B11: Total facilities | C11: # | D11: =SUM(D8:D10) -> 5 | E11: =SUM(E8:E10) -> 16 | F11: =SUM(F8:F10) -> 43 | G11: =SUM(G8:G10) -> 92 | H11: =SUM(H8:H10) -> 148
B12: New facilities (Taiwanese market) | C12: # | D12: =D8 -> 5 | E12: =E8-D8 -> 11 | F12: =F8-E8 -> 22 | G12: =G8-F8 -> 34 | H12: =H8-G8 -> 41
B13: New facilities (Korean pilot) | C13: # | D13: 0 | E13: 0 | F13: 5 | G13: =G9-F9 -> 10 | H13: =H9-G9 -> 10
B14: New facilities (Japanese pilot) | C14: # | D14: 0 | E14: 0 | F14: 0 | G14: 5 | H14: =H10-G10 -> 5
B15: New facilities | C15: # | D15: =SUM(D12:D14) -> 5 | E15: =SUM(E12:E14) -> 11 | F15: =SUM(F12:F14) -> 27 | G15: =SUM(G12:G14) -> 49 | H15: =SUM(H12:H14) -> 56
B16: Churn rate | C16: % | D16: 0 | E16: 0 | F16: 0.05 | G16: 0.05 | H16: 0.05
B17: Active facilities (Taiwanese market) | C17: # | D17: =INT(D11) -> 5 | E17: =INT(E11) -> 16 | F17: =INT(F12+E17*(1-F16)) -> 37 | G17: =INT(G12+F17*(1-G16)) -> 69 | H17: =INT(H12+G17*(1-H16)) -> 106
B18: Active facilities (Korean pilot) | C18: # | D18: 0 | E18: 0 | F18: =5 -> 5 | G18: 15 | H18: 25
B19: Active facilities (Japanese pilot) | C19: # | D19: 0 | E19: 0 | F19: 0 | G19: 5 | H19: 10
B20: Active facilities | C20: # | D20: =SUM(D17:D19) -> 5 | E20: =SUM(E17:E19) -> 16 | F20: =SUM(F17:F19) -> 42 | G20: =SUM(G17:G19) -> 89 | H20: =SUM(H17:H19) -> 141
B21: Residents per facility | C21: # | D21: 48 | E21: 48 | F21: 48 | G21: 48 | H21: 48
B23: Revenue Assumptions
B24: Hardware Revenue | C24: $ | D24: =(60*D21+325*3)*D15 -> 19275 | E24: =(60*E21+325*3)*E15 -> 42405 | F24: =(60*F21+325*3)*F15 -> 104085 | G24: =(60*G21+325*3)*G15 -> 188895 | H24: =(60*H21+325*3)*H15 -> 215880 | J24: (2) Wristband: US$ =60; Gateway: US$ =325$. Assumed that each facility needs 3 Gateways. Installation Fee is included in the selling price.
B25: Annual Service Revenue | C25: $ | D25: ='2-Monthly Service Revenue'!G20 -> 73125 | E25: ='2-Monthly Service Revenue'!G36 -> 295875 | F25: ='2-Monthly Service Revenue'!G52+'2-Monthly Service Revenue'!G103 -> 815083.32 | G25: ='2-Monthly Service Revenue'!G68+'2-Monthly Service Revenue'!G119 -> 1828609.3 | H25: ='2-Monthly Service Revenue'!G84+'2-Monthly Service Revenue'!G135 -> 3180077.8
B26: Total Revenue | C26: $ | D26: =SUM(D24:D25) -> 92400 | E26: =SUM(E24:E25) -> 338280 | F26: =SUM(F24:F25) -> 919168.32 | G26: =SUM(G24:G25) -> 2017504.3 | H26: =SUM(H24:H25) -> 3395957.8
B28: Cost Structure
B29: Variable
B30: Hardware COSG (per facility) | C30: $ | D30: =40*D21+120*3 -> 2280 | E30: =D30*103% -> 2348.4 | F30: =E30*103% -> 2418.852 | G30: =F30*103% -> 2491.4176 | H30: =G30*103% -> 2566.1601 | J30: (3) Wristband cost: US$ = 40; Gateway cost: US$ = 120. Assume that the cost of the Hardware COSG is affected by 3% inflation every year.
B31: Installation Cost (per facility) | C31: $ | D31: 300 | E31: =D31*103% -> 309 | F31: =E31*103% -> 318.27 | G31: =F31*103% -> 327.8181 | H31: =G31*103% -> 337.65264 | J31: (4) Assume that the cost of the Installation is affected by 3% inflation every year.
B32: Warranty Expense (variable portion) | C32: $ | D32: =D24*5% -> 963.75 | E32: =D32*103% -> 992.6625 | F32: =E32*103% -> 1022.4424 | G32: =F32*103% -> 1053.1156 | H32: =G32*103% -> 1084.7091 | J32: (5) Assume that 5% of Hardware Revenue is contributed to Warranty.
B33: Cloud Infrastructure (per resident) | C33: $ | D33: =0.5*12 -> 6 | E33: =D33*103% -> 6.18 | F33: =E33*103% -> 6.3654 | G33: =F33*103% -> 6.556362 | H33: =G33*103% -> 6.7530529 | J33: (6) Cloud Infrastructure: US$ = 0.5 per month per resident. Assume that the cost of the Cloud Infrastructure is affected by 3% inflation every year.
B34: Fixed
B35: Product R&D Cost | C35: $ | D35: 60000 | E35: =2%*E26 -> 6765.6 | F35: =2%*F26 -> 18383.366 | G35: =2%*G26 -> 40350.087 | H35: =2%*H26 -> 67919.156 | J35: (7) Coding cost is paid one-time to build Minimum Viable Product (MVP) at Y1. From Y2, 2% of Revenue is contributed to Product R&D.
B36: Certification & Compliance Cost | C36: $ | D36: 6500 | E36: 0 | F36: 6500 | G36: 6500 | H36: 0 | J36: (8) NCC, RoHS, IP67. US$6500 Expense in each year of Y3 & Y4 for Korean and Japanese Pilot.
B37: Salaries & Commission | C37: $ | D37: ='3-Human Resource'!E28 -> 121927.5 | E37: ='3-Human Resource'!F28 -> 127840.5 | F37: ='3-Human Resource'!G28 -> 203788.5 | G37: ='3-Human Resource'!H28 -> 317913 | H37: ='3-Human Resource'!I28 -> 362862.67 | J37: (9) Assumptions are in Personel Sheet.
B38: Rent & Utilities | C38: $ | D38: =250*'3-Human Resource'!E17*12 -> 15000 | E38: =250*'3-Human Resource'!F17*12 -> 15000 | F38: =250*'3-Human Resource'!G17*12 -> 27000 | G38: =250*'3-Human Resource'!H17*12 -> 42000 | H38: =250*'3-Human Resource'!I17*12 -> 48000 | J38: (10) Assume that Co-working space/ Renting lab is US$250 per person per month. Utilities is included.
B39: Office supplies and Equipment | C39: $ | D39: =1500*'3-Human Resource'!E17+5000 -> 12500 | E39: =1500*('3-Human Resource'!F17-'3-Human Resource'!E17)+5000 -> 5000 | F39: =1500*('3-Human Resource'!G17-'3-Human Resource'!F17)+5000 -> 11000 | G39: =1500*('3-Human Resource'!H17-'3-Human Resource'!G17)+5000 -> 12500 | H39: =1500*('3-Human Resource'!I17-'3-Human Resource'!H17)+5000 -> 8000 | J39: (11) Assume that each employee needs 01 laptop (One-time: US$1500 per laptop) and annually US$5000 for other tools & equipments.
B40: Marketing & Campaigns | C40: $ | D40: 8000 | E40: =D40*105% -> 8400 | F40: =E40*105%+5000 -> 13820 | G40: =F40*105%+5000*2 -> 24511 | H40: =G40*105%+5000*2 -> 35736.55 | J40: (12) Marketing & Campaigns expenses for Taiwanese Market is spent on 2 main expos annually (Medical Taiwan - Jun & Care Expo Taipei - Sep). Each expo is expected to have US$ 4000. The budget for Taiwanese Market is raised 5% each year. Marketing & Campaigns expenses for Korean & Japanese Pilot is US$ 5000/ year/ each.
B41: Travel and Entertainment | C41: $ | D41: 10000 | E41: =D41*105% -> 10500 | F41: =E41*105% -> 11025 | G41: =F41*105% -> 11576.25 | H41: =G41*105% -> 12155.062 | J41: (13) Travel and Entertainment for all markets is US$10000/ year. The budget is raised 5% each year.
B43: Tax Rate | C43: % | D43: 0.2 | E43: 0.2 | F43: 0.2 | G43: 0.2 | H43: 0.2
B45: Pro-Forma Income Statement
B46: Revenue | C46: $ | D46: =D26 -> 92400 | E46: =E26 -> 338280 | F46: =F26 -> 919168.32 | G46: =G26 -> 2017504.3 | H46: =H26 -> 3395957.8
B47: COGS | C47: $ | D47: =(D30*D20)+(D31*D20)+(D32)+(D33*D21*D20) -> 15303.75 | E47: =E30*E20+E31*E20+E32+E33*E21*E20 -> 48257.302 | F47: =F30*F20+F31*F20+F32+F33*F21*F20 -> 128814.21 | G47: =G30*G20+G31*G20+G32+G33*G21*G20 -> 279973.87 | H47: =H30*H20+H31*H20+H32+H33*H21*H20 -> 456226.97
B48: Gross Profit | C48: $ | D48: =D46-D47 -> 77096.25 | E48: =E46-E47 -> 290022.7 | F48: =F46-F47 -> 790354.1 | G48: =G46-G47 -> 1737530.5 | H48: =H46-H47 -> 2939730.8
B49: Gross Profit Margin | C49: % | D49: =D48/D46 -> 0.834375 | E49: =E48/E46 -> 0.85734509 | F49: =F48/F46 -> 0.85985786 | G49: =G48/G46 -> 0.86122763 | H49: =H48/H46 -> 0.86565588
B51: Operating Expenses - OpEx
B52: R&D Expenses | C52: $
B53: Salaries - Engineer | C53: $ | D53: ='3-Human Resource'!E20+'3-Human Resource'!E21 -> 72000 | E53: ='3-Human Resource'!F20+'3-Human Resource'!F21 -> 75600 | F53: ='3-Human Resource'!G20+'3-Human Resource'!G21 -> 79380 | G53: ='3-Human Resource'!H20+'3-Human Resource'!H21 -> 125023.5 | H53: ='3-Human Resource'!I20+'3-Human Resource'!I21 -> 131274.67
B54: Product Research and Development | C54: $ | D54: =D35 -> 60000 | E54: =E35 -> 6765.6 | F54: =F35 -> 18383.366 | G54: =G35 -> 40350.087 | H54: =H35 -> 67919.156
B55: Selling Expenses | C55: $
B56: Salaries - Business Development Employee | C56: $ | D56: ='3-Human Resource'!E23 -> 36000 | E56: ='3-Human Resource'!F23 -> 36000 | F56: ='3-Human Resource'!G23 -> 90000 | G56: ='3-Human Resource'!H23 -> 126000 | H56: ='3-Human Resource'!I23 -> 162000
B57: Sales Commission Expense | C57: $ | D57: ='3-Human Resource'!E24 -> 1927.5 | E57: ='3-Human Resource'!F24 -> 4240.5 | F57: ='3-Human Resource'!G24 -> 10408.5 | G57: ='3-Human Resource'!H24 -> 18889.5 | H57: ='3-Human Resource'!I24 -> 21588
B58: Travel and Entertainment | C58: $ | D58: =D41 -> 10000 | E58: =E41 -> 10500 | F58: =F41 -> 11025 | G58: =G41 -> 11576.25 | H58: =H41 -> 12155.062
B59: Marketing Expenses | C59: $
B60: Marketing & Campaigns Expense | C60: $ | D60: =D40 -> 8000 | E60: =E40 -> 8400 | F60: =F40 -> 13820 | G60: =G40 -> 24511 | H60: =H40 -> 35736.55
B61: Administrative Expenses | C61: $
B62: Salaries - Customer Support Employee | C62: $ | D62: ='3-Human Resource'!E27 -> 12000 | E62: ='3-Human Resource'!F27 -> 12000 | F62: ='3-Human Resource'!G27 -> 24000 | G62: ='3-Human Resource'!H27 -> 48000 | H62: ='3-Human Resource'!I27 -> 48000
B63: Rent & Utilities | C63: $ | D63: =D38 -> 15000 | E63: =E38 -> 15000 | F63: =F38 -> 27000 | G63: =G38 -> 42000 | H63: =H38 -> 48000
B64: Office supplies and Equipment | C64: $ | D64: =D39 -> 12500 | E64: =E39 -> 5000 | F64: =F39 -> 11000 | G64: =G39 -> 12500 | H64: =H39 -> 8000
B65: Total Operating Expense | C65: $ | D65: =SUM(D51:D64) -> 227427.5 | E65: =SUM(E51:E64) -> 173506.1 | F65: =SUM(F51:F64) -> 285016.87 | G65: =SUM(G51:G64) -> 448850.34 | H65: =SUM(H51:H64) -> 534673.44
B66: EBITDA | C66: $ | D66: =D48-D65 -> -150331.25 | E66: =E48-E65 -> 116516.6 | F66: =F48-F65 -> 505337.24 | G66: =G48-G65 -> 1288680.1 | H66: =H48-H65 -> 2405057.4
B67: Amortization | D67: =D36/5 -> 1300 | E67: =$D$36/5 -> 1300 | F67: =$D$36/5+F36/3 -> 3466.6667 | G67: =$D$36/5+F36/3+G36/2 -> 6716.6667 | H67: =$D$36/5+F36/3+G36/2 -> 6716.6667
B68: EBT | C68: $ | D68: =D66-D67 -> -151631.25 | E68: =E66-E67 -> 115216.6 | F68: =F66-F67 -> 501870.57 | G68: =G66-G67 -> 1281963.5 | H68: =H66-H67 -> 2398340.7
B69: Tax (20%) | C69: $ | D69: 0 | E69: 0 | F69: =F68*20% -> 100374.11 | G69: =G68*20% -> 256392.69 | H69: =H68*20% -> 479668.14
B70: Net Income (Loss) | C70: $ | D70: =D68-D69 -> -151631.25 | E70: =E68-E69 -> 115216.6 | F70: =F68-F69 -> 401496.46 | G70: =G68-G69 -> 1025570.8 | H70: =H68-H69 -> 1918672.6

Sheet 2-Monthly Service Revenue
B2: WaveCare Monthly Service Revenue Cohort Assumption
B3: Assumptions | C3: Active from Y-1 | D3: New Signed | E3: Churn Rate | F3: Cumulative Total Active | G3: Monthly service revenue
B5: Taiwanese Market
B6: Year 1
B7: Month
B8: Jan | C8: 0 | D8: ='1-Financial Model'!$D$15/12 -> 0.41666667 | E8: 0 | F8: =D8 -> 0.41666667 | G8: =F8*'1-Financial Model'!$D$21*30000/32*5% -> 937.5
B9: Feb | C9: 0 | D9: ='1-Financial Model'!$D$15/12 -> 0.41666667 | E9: 0 | F9: =C8+F8+D9 -> 0.83333333 | G9: =F9*'1-Financial Model'!$D$21*30000/32*5% -> 1875
B10: Mar | C10: 0 | D10: ='1-Financial Model'!$D$15/12 -> 0.41666667 | E10: 0 | F10: =C9+F9+D10 -> 1.25 | G10: =F10*'1-Financial Model'!$D$21*30000/32*5% -> 2812.5
B11: Apr | C11: 0 | D11: ='1-Financial Model'!$D$15/12 -> 0.41666667 | E11: 0 | F11: =C10+F10+D11 -> 1.6666667 | G11: =F11*'1-Financial Model'!$D$21*30000/32*5% -> 3750
B12: May | C12: 0 | D12: ='1-Financial Model'!$D$15/12 -> 0.41666667 | E12: 0 | F12: =C11+F11+D12 -> 2.0833333 | G12: =F12*'1-Financial Model'!$D$21*30000/32*5% -> 4687.5
B13: Jun | C13: 0 | D13: ='1-Financial Model'!$D$15/12 -> 0.41666667 | E13: 0 | F13: =C12+F12+D13 -> 2.5 | G13: =F13*'1-Financial Model'!$D$21*30000/32*5% -> 5625
B14: Jul | C14: 0 | D14: ='1-Financial Model'!$D$15/12 -> 0.41666667 | E14: 0 | F14: =C13+F13+D14 -> 2.9166667 | G14: =F14*'1-Financial Model'!$D$21*30000/32*5% -> 6562.5
B15: Aug | C15: 0 | D15: ='1-Financial Model'!$D$15/12 -> 0.41666667 | E15: 0 | F15: =C14+F14+D15 -> 3.3333333 | G15: =F15*'1-Financial Model'!$D$21*30000/32*5% -> 7500
B16: Sep | C16: 0 | D16: ='1-Financial Model'!$D$15/12 -> 0.41666667 | E16: 0 | F16: =C15+F15+D16 -> 3.75 | G16: =F16*'1-Financial Model'!$D$21*30000/32*5% -> 8437.5
B17: Oct | C17: 0 | D17: ='1-Financial Model'!$D$15/12 -> 0.41666667 | E17: 0 | F17: =C16+F16+D17 -> 4.1666667 | G17: =F17*'1-Financial Model'!$D$21*30000/32*5% -> 9375
B18: Nov | C18: 0 | D18: ='1-Financial Model'!$D$15/12 -> 0.41666667 | E18: 0 | F18: =C17+F17+D18 -> 4.5833333 | G18: =F18*'1-Financial Model'!$D$21*30000/32*5% -> 10312.5
B19: Dec | C19: 0 | D19: ='1-Financial Model'!$D$15/12 -> 0.41666667 | E19: 0 | F19: =C18+F18+D19 -> 5 | G19: =F19*'1-Financial Model'!$D$21*30000/32*5% -> 11250
B20: Total Year 1 | D20: =SUM(D8:D19) -> 5 | F20: =F19 -> 5 | G20: =SUM(G8:G19) -> 73125
B22: Year 2
B23: Month
B24: Jan | C24: =$D$20 -> 5 | D24: ='1-Financial Model'!$E$15/12 -> 0.91666667 | E24: 0 | F24: =C24+D24 -> 5.9166667 | G24: =F24*'1-Financial Model'!$D$21*30000/32*5% -> 13312.5
B25: Feb | C25: =$D$20 -> 5 | D25: ='1-Financial Model'!$E$15/12 -> 0.91666667 | E25: 0 | F25: =F24+D25 -> 6.8333333 | G25: =F25*'1-Financial Model'!$D$21*30000/32*5% -> 15375
B26: Mar | C26: =$D$20 -> 5 | D26: ='1-Financial Model'!$E$15/12 -> 0.91666667 | E26: 0 | F26: =F25+D26 -> 7.75 | G26: =F26*'1-Financial Model'!$D$21*30000/32*5% -> 17437.5
B27: Apr | C27: =$D$20 -> 5 | D27: ='1-Financial Model'!$E$15/12 -> 0.91666667 | E27: 0 | F27: =F26+D27 -> 8.6666667 | G27: =F27*'1-Financial Model'!$D$21*30000/32*5% -> 19500
B28: May | C28: =$D$20 -> 5 | D28: ='1-Financial Model'!$E$15/12 -> 0.91666667 | E28: 0 | F28: =F27+D28 -> 9.5833333 | G28: =F28*'1-Financial Model'!$D$21*30000/32*5% -> 21562.5
B29: Jun | C29: =$D$20 -> 5 | D29: ='1-Financial Model'!$E$15/12 -> 0.91666667 | E29: 0 | F29: =F28+D29 -> 10.5 | G29: =F29*'1-Financial Model'!$D$21*30000/32*5% -> 23625
B30: Jul | C30: =$D$20 -> 5 | D30: ='1-Financial Model'!$E$15/12 -> 0.91666667 | E30: 0 | F30: =F29+D30 -> 11.416667 | G30: =F30*'1-Financial Model'!$D$21*30000/32*5% -> 25687.5
B31: Aug | C31: =$D$20 -> 5 | D31: ='1-Financial Model'!$E$15/12 -> 0.91666667 | E31: 0 | F31: =F30+D31 -> 12.333333 | G31: =F31*'1-Financial Model'!$D$21*30000/32*5% -> 27750
B32: Sep | C32: =$D$20 -> 5 | D32: ='1-Financial Model'!$E$15/12 -> 0.91666667 | E32: 0 | F32: =F31+D32 -> 13.25 | G32: =F32*'1-Financial Model'!$D$21*30000/32*5% -> 29812.5
B33: Oct | C33: =$D$20 -> 5 | D33: ='1-Financial Model'!$E$15/12 -> 0.91666667 | E33: 0 | F33: =F32+D33 -> 14.166667 | G33: =F33*'1-Financial Model'!$D$21*30000/32*5% -> 31875
B34: Nov | C34: =$D$20 -> 5 | D34: ='1-Financial Model'!$E$15/12 -> 0.91666667 | E34: 0 | F34: =F33+D34 -> 15.083333 | G34: =F34*'1-Financial Model'!$D$21*30000/32*5% -> 33937.5
B35: Dec | C35: =$D$20 -> 5 | D35: ='1-Financial Model'!$E$15/12 -> 0.91666667 | E35: 0 | F35: =F34+D35 -> 16 | G35: =F35*'1-Financial Model'!$D$21*30000/32*5% -> 36000
B36: Total Year 2 | D36: =SUM(D24:D35) -> 11 | F36: =F35 -> 16 | G36: =SUM(G24:G35) -> 295875
B38: Year 3
B39: Month
B40: Jan | C40: =$F$36 -> 16 | D40: ='1-Financial Model'!$F$12/12 -> 1.8333333 | E40: =(1-'1-Financial Model'!$F$16)^(1/12)-1 -> -0.0042653188 | F40: =C40+D40+C40*E40 -> 17.765088 | G40: =F40*'1-Financial Model'!$D$21*30000/32*5% -> 39971.449
B41: Feb | C41: =C40+C40*E40 -> 15.931755 | D41: ='1-Financial Model'!$F$12/12 -> 1.8333333 | E41: =(1-'1-Financial Model'!$F$16)^(1/12)-1 -> -0.0042653188 | F41: =F40+D41+C41*E41 -> 19.530468 | G41: =F41*'1-Financial Model'!$D$21*30000/32*5% -> 43943.552
B42: Mar | C42: =C41+C41*E41 -> 15.863801 | D42: ='1-Financial Model'!$F$12/12 -> 1.8333333 | E42: =(1-'1-Financial Model'!$F$16)^(1/12)-1 -> -0.0042653188 | F42: =F41+D42+C42*E42 -> 21.296137 | G42: =F42*'1-Financial Model'!$D$21*30000/32*5% -> 47916.308
B43: Apr | C43: =C42+C42*E42 -> 15.796137 | D43: ='1-Financial Model'!$F$12/12 -> 1.8333333 | E43: =(1-'1-Financial Model'!$F$16)^(1/12)-1 -> -0.0042653188 | F43: =F42+D43+C43*E43 -> 23.062094 | G43: =F43*'1-Financial Model'!$D$21*30000/32*5% -> 51889.713
B44: May | C44: =C43+C43*E43 -> 15.728761 | D44: ='1-Financial Model'!$F$12/12 -> 1.8333333 | E44: =(1-'1-Financial Model'!$F$16)^(1/12)-1 -> -0.0042653188 | F44: =F43+D44+C44*E44 -> 24.82834 | G44: =F44*'1-Financial Model'!$D$21*30000/32*5% -> 55863.764
B45: Jun | C45: =C44+C44*E44 -> 15.661673 | D45: ='1-Financial Model'!$F$12/12 -> 1.8333333 | E45: =(1-'1-Financial Model'!$F$16)^(1/12)-1 -> -0.0042653188 | F45: =F44+D45+C45*E45 -> 26.594871 | G45: =F45*'1-Financial Model'!$D$21*30000/32*5% -> 59838.46
B46: Jul | C46: =C45+C45*E45 -> 15.594871 | D46: ='1-Financial Model'!$F$12/12 -> 1.8333333 | E46: =(1-'1-Financial Model'!$F$16)^(1/12)-1 -> -0.0042653188 | F46: =F45+D46+C46*E46 -> 28.361687 | G46: =F46*'1-Financial Model'!$D$21*30000/32*5% -> 63813.796
B47: Aug | C47: =C46+C46*E46 -> 15.528354 | D47: ='1-Financial Model'!$F$12/12 -> 1.8333333 | E47: =(1-'1-Financial Model'!$F$16)^(1/12)-1 -> -0.0042653188 | F47: =F46+D47+C47*E47 -> 30.128787 | G47: =F47*'1-Financial Model'!$D$21*30000/32*5% -> 67789.771
B48: Sep | C48: =C47+C47*E47 -> 15.46212 | D48: ='1-Financial Model'!$F$12/12 -> 1.8333333 | E48: =(1-'1-Financial Model'!$F$16)^(1/12)-1 -> -0.0042653188 | F48: =F47+D48+C48*E48 -> 31.89617 | G48: =F48*'1-Financial Model'!$D$21*30000/32*5% -> 71766.382
B49: Oct | C49: =C48+C48*E48 -> 15.39617 | D49: ='1-Financial Model'!$F$12/12 -> 1.8333333 | E49: =(1-'1-Financial Model'!$F$16)^(1/12)-1 -> -0.0042653188 | F49: =F48+D49+C49*E49 -> 33.663833 | G49: =F49*'1-Financial Model'!$D$21*30000/32*5% -> 75743.625
B50: Nov | C50: =C49+C49*E49 -> 15.3305 | D50: ='1-Financial Model'!$F$12/12 -> 1.8333333 | E50: =(1-'1-Financial Model'!$F$16)^(1/12)-1 -> -0.0042653188 | F50: =F49+D50+C50*E50 -> 35.431777 | G50: =F50*'1-Financial Model'!$D$21*30000/32*5% -> 79721.499
B51: Dec | C51: =C50+C50*E50 -> 15.265111 | D51: ='1-Financial Model'!$F$12/12 -> 1.8333333 | E51: =(1-'1-Financial Model'!$F$16)^(1/12)-1 -> -0.0042653188 | F51: =F50+D51+C51*E51 -> 37.2 | G51: =F51*'1-Financial Model'!$D$21*30000/32*5% -> 83700
B52: Total Year 3 | D52: =SUM(D40:D51) -> 22 | F52: =F51 -> 37.2 | G52: =SUM(G40:G51) -> 741958.32
B54: Year 4
B55: Month
B56: Jan | C56: =F52 -> 37.2 | D56: ='1-Financial Model'!$G$12/12 -> 2.8333333 | E56: =(1-'1-Financial Model'!$F$16)^(1/12)-1 -> -0.0042653188 | F56: =C56+C56*E56+D56 -> 39.874663 | G56: =F56*'1-Financial Model'!$D$21*30000/32*5% -> 89717.993
B57: Feb | C57: =C56+C56*E57 -> 37.04133 | D57: ='1-Financial Model'!$G$12/12 -> 2.8333333 | E57: =(1-'1-Financial Model'!$F$16)^(1/12)-1 -> -0.0042653188 | F57: =F56+C57*E57+D57 -> 42.550004 | G57: =F57*'1-Financial Model'!$D$21*30000/32*5% -> 95737.508
B58: Mar | C58: =C57+C57*E58 -> 36.883337 | D58: ='1-Financial Model'!$G$12/12 -> 2.8333333 | E58: =(1-'1-Financial Model'!$F$16)^(1/12)-1 -> -0.0042653188 | F58: =F57+C58*E58+D58 -> 45.226018 | G58: =F58*'1-Financial Model'!$D$21*30000/32*5% -> 101758.54
B59: Apr | C59: =C58+C58*E59 -> 36.726018 | D59: ='1-Financial Model'!$G$12/12 -> 2.8333333 | E59: =(1-'1-Financial Model'!$F$16)^(1/12)-1 -> -0.0042653188 | F59: =F58+C59*E59+D59 -> 47.902703 | G59: =F59*'1-Financial Model'!$D$21*30000/32*5% -> 107781.08
B60: May | C60: =C59+C59*E60 -> 36.56937 | D60: ='1-Financial Model'!$G$12/12 -> 2.8333333 | E60: =(1-'1-Financial Model'!$F$16)^(1/12)-1 -> -0.0042653188 | F60: =F59+C60*E60+D60 -> 50.580056 | G60: =F60*'1-Financial Model'!$D$21*30000/32*5% -> 113805.13
B61: Jun | C61: =C60+C60*E61 -> 36.41339 | D61: ='1-Financial Model'!$G$12/12 -> 2.8333333 | E61: =(1-'1-Financial Model'!$F$16)^(1/12)-1 -> -0.0042653188 | F61: =F60+C61*E61+D61 -> 53.258075 | G61: =F61*'1-Financial Model'!$D$21*30000/32*5% -> 119830.67
B62: Jul | C62: =C61+C61*E62 -> 36.258075 | D62: ='1-Financial Model'!$G$12/12 -> 2.8333333 | E62: =(1-'1-Financial Model'!$F$16)^(1/12)-1 -> -0.0042653188 | F62: =F61+C62*E62+D62 -> 55.936756 | G62: =F62*'1-Financial Model'!$D$21*30000/32*5% -> 125857.7
B63: Aug | C63: =C62+C62*E63 -> 36.103423 | D63: ='1-Financial Model'!$G$12/12 -> 2.8333333 | E63: =(1-'1-Financial Model'!$F$16)^(1/12)-1 -> -0.0042653188 | F63: =F62+C63*E63+D63 -> 58.616097 | G63: =F63*'1-Financial Model'!$D$21*30000/32*5% -> 131886.22
B64: Sep | C64: =C63+C63*E64 -> 35.94943 | D64: ='1-Financial Model'!$G$12/12 -> 2.8333333 | E64: =(1-'1-Financial Model'!$F$16)^(1/12)-1 -> -0.0042653188 | F64: =F63+C64*E64+D64 -> 61.296094 | G64: =F64*'1-Financial Model'!$D$21*30000/32*5% -> 137916.21
B65: Oct | C65: =C64+C64*E65 -> 35.796094 | D65: ='1-Financial Model'!$G$12/12 -> 2.8333333 | E65: =(1-'1-Financial Model'!$F$16)^(1/12)-1 -> -0.0042653188 | F65: =F64+C65*E65+D65 -> 63.976746 | G65: =F65*'1-Financial Model'!$D$21*30000/32*5% -> 143947.68
B66: Nov | C66: =C65+C65*E66 -> 35.643413 | D66: ='1-Financial Model'!$G$12/12 -> 2.8333333 | E66: =(1-'1-Financial Model'!$F$16)^(1/12)-1 -> -0.0042653188 | F66: =F65+C66*E66+D66 -> 66.658049 | G66: =F66*'1-Financial Model'!$D$21*30000/32*5% -> 149980.61
B67: Dec | C67: =C66+C66*E67 -> 35.491382 | D67: ='1-Financial Model'!$G$12/12 -> 2.8333333 | E67: =(1-'1-Financial Model'!$F$16)^(1/12)-1 -> -0.0042653188 | F67: =F66+C67*E67+D67 -> 69.34 | G67: =F67*'1-Financial Model'!$D$21*30000/32*5% -> 156015
B68: Total Year 4 | D68: =SUM(D56:D67) -> 34 | F68: =F67 -> 69.34 | G68: =SUM(G56:G67) -> 1474234.3
B70: Year 5
B71: Month
B72: Jan | C72: =F68 -> 69.34 | D72: ='1-Financial Model'!$H$12/12 -> 3.4166667 | E72: =(1-'1-Financial Model'!$F$16)^(1/12)-1 -> -0.0042653188 | F72: =C72+D72+C72*E72 -> 72.460909 | G72: =F72*'1-Financial Model'!$D$21*30000/32*5% -> 163037.05
B73: Feb | C73: =C72+C72*E72 -> 69.044243 | D73: ='1-Financial Model'!$H$12/12 -> 3.4166667 | E73: =(1-'1-Financial Model'!$F$16)^(1/12)-1 -> -0.0042653188 | F73: =F72+D73+C73*E73 -> 75.58308 | G73: =F73*'1-Financial Model'!$D$21*30000/32*5% -> 170061.93
B74: Mar | C74: =C73+C73*E73 -> 68.749747 | D74: ='1-Financial Model'!$H$12/12 -> 3.4166667 | E74: =(1-'1-Financial Model'!$F$16)^(1/12)-1 -> -0.0042653188 | F74: =F73+D74+C74*E74 -> 78.706508 | G74: =F74*'1-Financial Model'!$D$21*30000/32*5% -> 177089.64
B75: Apr | C75: =C74+C74*E74 -> 68.456508 | D75: ='1-Financial Model'!$H$12/12 -> 3.4166667 | E75: =(1-'1-Financial Model'!$F$16)^(1/12)-1 -> -0.0042653188 | F75: =F74+D75+C75*E75 -> 81.831185 | G75: =F75*'1-Financial Model'!$D$21*30000/32*5% -> 184120.17
B76: May | C76: =C75+C75*E75 -> 68.164519 | D76: ='1-Financial Model'!$H$12/12 -> 3.4166667 | E76: =(1-'1-Financial Model'!$F$16)^(1/12)-1 -> -0.0042653188 | F76: =F75+D76+C76*E76 -> 84.957109 | G76: =F76*'1-Financial Model'!$D$21*30000/32*5% -> 191153.49
B77: Jun | C77: =C76+C76*E76 -> 67.873775 | D77: ='1-Financial Model'!$H$12/12 -> 3.4166667 | E77: =(1-'1-Financial Model'!$F$16)^(1/12)-1 -> -0.0042653188 | F77: =F76+D77+C77*E77 -> 88.084272 | G77: =F77*'1-Financial Model'!$D$21*30000/32*5% -> 198189.61
B78: Jul | C78: =C77+C77*E77 -> 67.584272 | D78: ='1-Financial Model'!$H$12/12 -> 3.4166667 | E78: =(1-'1-Financial Model'!$F$16)^(1/12)-1 -> -0.0042653188 | F78: =F77+D78+C78*E78 -> 91.21267 | G78: =F78*'1-Financial Model'!$D$21*30000/32*5% -> 205228.51
B79: Aug | C79: =C78+C78*E78 -> 67.296004 | D79: ='1-Financial Model'!$H$12/12 -> 3.4166667 | E79: =(1-'1-Financial Model'!$F$16)^(1/12)-1 -> -0.0042653188 | F79: =F78+D79+C79*E79 -> 94.342298 | G79: =F79*'1-Financial Model'!$D$21*30000/32*5% -> 212270.17
B80: Sep | C80: =C79+C79*E79 -> 67.008965 | D80: ='1-Financial Model'!$H$12/12 -> 3.4166667 | E80: =(1-'1-Financial Model'!$F$16)^(1/12)-1 -> -0.0042653188 | F80: =F79+D80+C80*E80 -> 97.47315 | G80: =F80*'1-Financial Model'!$D$21*30000/32*5% -> 219314.59
B81: Oct | C81: =C80+C80*E80 -> 66.72315 | D81: ='1-Financial Model'!$H$12/12 -> 3.4166667 | E81: =(1-'1-Financial Model'!$F$16)^(1/12)-1 -> -0.0042653188 | F81: =F80+D81+C81*E81 -> 100.60522 | G81: =F81*'1-Financial Model'!$D$21*30000/32*5% -> 226361.75
B82: Nov | C82: =C81+C81*E81 -> 66.438555 | D82: ='1-Financial Model'!$H$12/12 -> 3.4166667 | E82: =(1-'1-Financial Model'!$F$16)^(1/12)-1 -> -0.0042653188 | F82: =F81+D82+C82*E82 -> 103.73851 | G82: =F82*'1-Financial Model'!$D$21*30000/32*5% -> 233411.64
B83: Dec | C83: =C82+C82*E82 -> 66.155173 | D83: ='1-Financial Model'!$H$12/12 -> 3.4166667 | E83: =(1-'1-Financial Model'!$F$16)^(1/12)-1 -> -0.0042653188 | F83: =F82+D83+C83*E83 -> 106.873 | G83: =F83*'1-Financial Model'!$D$21*30000/32*5% -> 240464.25
B84: Total Year 5 | D84: =SUM(D72:D83) -> 41 | F84: =F83 -> 106.873 | G84: =SUM(G72:G83) -> 2420702.8
B86: Total Taiwanese Market's Revenue | G86: =G20+G36+G52+G68+G84 -> 5005895.5
B88: Korean & Japanese Pilot
B89: Year 3
B90: Month
B91: Jan | C91: 0 | D91: ='1-Financial Model'!$F$18/12 -> 0.41666667 | E91: 0 | F91: =C91+D91+C91*E91 -> 0.41666667 | G91: =F91*'1-Financial Model'!$D$21*30000/32*5% -> 937.5
B92: Feb | C92: 0 | D92: ='1-Financial Model'!$F$18/12 -> 0.41666667 | E92: 0 | F92: =F91+D92+C92*E92 -> 0.83333333 | G92: =F92*'1-Financial Model'!$D$21*30000/32*5% -> 1875
B93: Mar | C93: 0 | D93: ='1-Financial Model'!$F$18/12 -> 0.41666667 | E93: 0 | F93: =F92+D93+C93*E93 -> 1.25 | G93: =F93*'1-Financial Model'!$D$21*30000/32*5% -> 2812.5
B94: Apr | C94: 0 | D94: ='1-Financial Model'!$F$18/12 -> 0.41666667 | E94: 0 | F94: =F93+D94+C94*E94 -> 1.6666667 | G94: =F94*'1-Financial Model'!$D$21*30000/32*5% -> 3750
B95: May | C95: 0 | D95: ='1-Financial Model'!$F$18/12 -> 0.41666667 | E95: 0 | F95: =F94+D95+C95*E95 -> 2.0833333 | G95: =F95*'1-Financial Model'!$D$21*30000/32*5% -> 4687.5
B96: Jun | C96: 0 | D96: ='1-Financial Model'!$F$18/12 -> 0.41666667 | E96: 0 | F96: =F95+D96+C96*E96 -> 2.5 | G96: =F96*'1-Financial Model'!$D$21*30000/32*5% -> 5625
B97: Jul | C97: 0 | D97: ='1-Financial Model'!$F$18/12 -> 0.41666667 | E97: 0 | F97: =F96+D97+C97*E97 -> 2.9166667 | G97: =F97*'1-Financial Model'!$D$21*30000/32*5% -> 6562.5
B98: Aug | C98: 0 | D98: ='1-Financial Model'!$F$18/12 -> 0.41666667 | E98: 0 | F98: =F97+D98+C98*E98 -> 3.3333333 | G98: =F98*'1-Financial Model'!$D$21*30000/32*5% -> 7500
B99: Sep | C99: 0 | D99: ='1-Financial Model'!$F$18/12 -> 0.41666667 | E99: 0 | F99: =F98+D99+C99*E99 -> 3.75 | G99: =F99*'1-Financial Model'!$D$21*30000/32*5% -> 8437.5
B100: Oct | C100: 0 | D100: ='1-Financial Model'!$F$18/12 -> 0.41666667 | E100: 0 | F100: =F99+D100+C100*E100 -> 4.1666667 | G100: =F100*'1-Financial Model'!$D$21*30000/32*5% -> 9375
B101: Nov | C101: 0 | D101: ='1-Financial Model'!$F$18/12 -> 0.41666667 | E101: 0 | F101: =F100+D101+C101*E101 -> 4.5833333 | G101: =F101*'1-Financial Model'!$D$21*30000/32*5% -> 10312.5
B102: Dec | C102: 0 | D102: ='1-Financial Model'!$F$18/12 -> 0.41666667 | E102: 0 | F102: =F101+D102+C102*E102 -> 5 | G102: =F102*'1-Financial Model'!$D$21*30000/32*5% -> 11250
B103: Total Year 3 | D103: =SUM(D91:D102) -> 5 | F103: =F102 -> 5 | G103: =SUM(G91:G102) -> 73125
B105: Year 4
B106: Month
B107: Jan | C107: =F103 -> 5 | D107: =('1-Financial Model'!$G$18-'1-Financial Model'!$F$18)/12+'1-Financial Model'!$G$19/12 -> 1.25 | E107: 0 | F107: =C107+D107+C107*E107 -> 6.25 | G107: =F107*'1-Financial Model'!$D$21*30000/32*5% -> 14062.5
B108: Feb | C108: =C107+C107*E107 -> 5 | D108: =('1-Financial Model'!$G$18-'1-Financial Model'!$F$18)/12+'1-Financial Model'!$G$19/12 -> 1.25 | E108: 0 | F108: =F107+D108+C108*E108 -> 7.5 | G108: =F108*'1-Financial Model'!$D$21*30000/32*5% -> 16875
B109: Mar | C109: =C108+C108*E108 -> 5 | D109: =('1-Financial Model'!$G$18-'1-Financial Model'!$F$18)/12+'1-Financial Model'!$G$19/12 -> 1.25 | E109: 0 | F109: =F108+D109+C109*E109 -> 8.75 | G109: =F109*'1-Financial Model'!$D$21*30000/32*5% -> 19687.5
...

Sheet 3-Human Resource
B2: WaveCare Personel Forecast
E3: 2027 | F3: 2028 | G3: 2029 | H3: 2030 | I3: 2031
B4: Assumptions | C4: Unit | D4: Base Salary | E4: Year 1 | F4: Year 2 | G4: Year 3 | H4: Year 4 | I4: Year 5 | K4: Note
B5: Quantity Assumptions
B6: Engineer
B7: Firmware Engineer | C7: # | E7: 1 | F7: 1 | G7: 1 | H7: 1 | I7: 1
B8: Backend Engineer | C8: # | E8: 1 | F8: 1 | G8: 1 | H8: 2 | I8: 2
B9: Business Development
B10: Business Development Employee (Taiwanese Market) | C10: # | E10: 2 | F10: 2 | G10: 3 | H10: 3 | I10: 4 | K10: (1) Commission is based on 5% revenue of the Hardware.
B11: Business Development Employee (Korean Pilot) | C11: # | E11: 0 | F11: 0 | G11: 2 | H11: 2 | I11: 3
B12: Business Development Employee (Japanese Pilot) | C12: # | E12: 0 | F12: 0 | G12: 0 | H12: 2 | I12: 2
B13: Admin/ Support
B14: Customer Support Employee (Taiwanese Market) | C14: # | E14: 1 | F14: 1 | G14: 1 | H14: 2 | I14: 2
B15: Customer Support Employee (Korean Pilot) | C15: # | E15: 0 | F15: 0 | G15: 1 | H15: 1 | I15: 1
B16: Customer Support Employee (Japanese Pilot) | C16: # | E16: 0 | F16: 0 | G16: 0 | H16: 1 | I16: 1
B17: Total | C17: # | E17: =SUM(E7:E14) -> 5 | F17: =SUM(F7:F14) -> 5 | G17: =SUM(G7:G16) -> 9 | H17: =SUM(H7:H16) -> 14 | I17: =SUM(I7:I16) -> 16
B18: Salaries
B19: Engineer
B20: Firmware Engineer ($3000 per month) | C20: $ | D20: 3000 | E20: =D20*E7*12 -> 36000 | F20: =E20*105%/E7*F7 -> 37800 | G20: =F20*105%/F7*G7 -> 39690 | H20: =G20*105%/G7*H7 -> 41674.5 | I20: =H20*105%/H7*I7 -> 43758.225 | K20: (2) Assume that Salary Increase Rate is 5% annually.
B21: Backend Engineer ($3000 per month) | C21: $ | D21: 3000 | E21: =D21*E8*12 -> 36000 | F21: =E21*105%/E8*F8 -> 37800 | G21: =F21*105%/F8*G8 -> 39690 | H21: =G21*105%/G8*H8 -> 83349 | I21: =H21*105%/H8*I8 -> 87516.45
B22: Business Development
B23: Business Development Employee ($1500 per month) | C23: $ | D23: 1500 | E23: =D23*SUM(E10:E12)*12 -> 36000 | F23: =$D$23*12*SUM(F10:F12) -> 36000 | G23: =$D$23*12*SUM(G10:G12) -> 90000 | H23: =$D$23*12*SUM(H10:H12) -> 126000 | I23: =$D$23*12*SUM(I10:I12) -> 162000
B24: Business Development Employee's Commission | C24: $ | E24: =10%*'1-Financial Model'!D24 -> 1927.5 | F24: =10%*'1-Financial Model'!E24 -> 4240.5 | G24: =10%*'1-Financial Model'!F24 -> 10408.5 | H24: =10%*'1-Financial Model'!G24 -> 18889.5 | I24: =10%*'1-Financial Model'!H24 -> 21588 | K24: (3) Assume that Commission is based on 10% of the Hardware Revenue.
B25: Total | E25: =SUM(E23:E24) -> 37927.5 | F25: =SUM(F23:F24) -> 40240.5 | G25: =SUM(G23:G24) -> 100408.5 | H25: =SUM(H23:H24) -> 144889.5 | I25: =SUM(I23:I24) -> 183588
B26: Admin/ Support
B27: Customer Support Employee ($1000 per month) | C27: $ | D27: 1000 | E27: =$D$27*SUM(E14:E16)*12 -> 12000 | F27: =$D$27*SUM(F14:F16)*12 -> 12000 | G27: =$D$27*SUM(G14:G16)*12 -> 24000 | H27: =$D$27*SUM(H14:H16)*12 -> 48000 | I27: =$D$27*SUM(I14:I16)*12 -> 48000
B28: Total Salaries | C28: $ | E28: =E20+E21+E25+E27 -> 121927.5 | F28: =F20+F21+F25+F27 -> 127840.5 | G28: =G20+G21+G25+G27 -> 203788.5 | H28: =H20+H21+H25+H27 -> 317913 | I28: =I20+I21+I25+I27 -> 362862.67

Sheet 4-BD Scaling 
B2: Year | C2: BD | D2: Expected Lead/BD/Year | E2: Close rate | F2: New Sales
B3: Taiwanese Market
B4: Y1 | C4: 2 | D4: 18 | E4: 0.15 | F4: =C4*D4*E4 -> 5.4
B5: Y2 | C5: 2 | D5: 28 | E5: 0.2 | F5: =C5*D5*E5 -> 11.2
B6: Y3 | C6: 3 | D6: 34 | E6: 0.22 | F6: =C6*D6*E6 -> 22.44
B7: Y4 | C7: 3 | D7: 50 | E7: 0.23 | F7: =C7*D7*E7 -> 34.5
B8: Y5 | C8: 4 | D8: 40 | E8: 0.25 | F8: =C8*D8*E8 -> 40
B9: Total | F9: =SUM(F4:F8) -> 113.54
B11: Korean Pilot
B12: Y1 | C12: 0 | D12: 0 | E12: 0 | F12: =C12*D12*E12 -> 0
B13: Y2 | C13: 0 | D13: 0 | E13: 0 | F13: =C13*D13*E13 -> 0
B14: Y3 | C14: 2 | D14: 17 | E14: 0.15 | F14: =C14*D14*E14 -> 5.1
B15: Y4 | C15: 2 | D15: 25 | E15: 0.2 | F15: =C15*D15*E15 -> 10
B16: Y5 | C16: 2 | D16: 25 | E16: 0.2 | F16: =C16*D16*E16 -> 10
B17: Total | F17: =SUM(F12:F16) -> 25.1
B19: Japanese Pilot
B20: Y1 | C20: 0 | D20: 0 | E20: 0 | F20: =C20*D20*E20 -> 0
B21: Y2 | C21: 0 | D21: 0 | E21: 0 | F21: =C21*D21*E21 -> 0
B22: Y3 | C22: 0 | D22: 0 | E22: 0 | F22: =C22*D22*E22 -> 0
B23: Y4 | C23: 2 | D23: 25 | E23: 0.1 | F23: =C23*D23*E23 -> 5
B24: Y5 | C24: 2 | D24: 25 | E24: 0.12 | F24: =C24*D24*E24 -> 6
B25: Total | F25: =SUM(F20:F24) -> 11

Sheet 5-NPV IRR
B2: Year | C2: CF | D2: WACC | E2: Discount Factor | F2: NPV
B3: 0 | C3: =-400000 -> -400000 | D3: 0.2 | E3: =1/(1+D3)^B3 -> 1 | F3: =C3*E3 -> -400000
B4: 1 | C4: ='1-Financial Model'!D70 -> -151631.25 | D4: 0.2 | E4: =1/(1+D4)^B4 -> 0.83333333 | F4: =C4*E4 -> -126359.38
B5: 2 | C5: ='1-Financial Model'!E70 -> 115216.6 | D5: 0.2 | E5: =1/(1+D5)^B5 -> 0.69444444 | F5: =C5*E5 -> 80011.526
B6: 3 | C6: ='1-Financial Model'!F70 -> 401496.46 | D6: 0.2 | E6: =1/(1+D6)^B6 -> 0.5787037 | F6: =C6*E6 -> 232347.49
B7: 4 | C7: ='1-Financial Model'!G70 -> 1025570.8 | D7: 0.2 | E7: =1/(1+D7)^B7 -> 0.48225309 | F7: =C7*E7 -> 494584.67
B8: 5 | C8: ='1-Financial Model'!H70 -> 1918672.6 | D8: 0.2 | E8: =1/(1+D8)^B8 -> 0.40187757 | F8: =C8*E8 -> 771071.48
B9: Total NPV | F9: =SUM(F3:F8) -> 1051655.8
B11: IRR | C11: =IRR(C3:C8) -> 0.58946054

Sheet 6-Reference
A1: Nursing Institute Report | B1: https://nurse.mohw.gov.tw/mp-2.html
A2: Elderly Instution Report | B2: https://stis.mohw.gov.tw/HWSDweb/common/CommonQuery.aspx?code=G&id=69&utm_source=chatgpt.com
A3: Benchmark for prices | B3: https://www.ncoa.org/product-resources/medical-alert-systems/best-medical-alert-systems-with-fall-detection/?utm_source=chatgpt.com
A4: Nursing homes price/month | B4: https://www.aftygh.gov.tw/english-dep/nursing-home/?utm_source=chatgpt.com https://chnh.mohw.gov.tw/eng/content/index.aspx?Parser=1%2C14%2C95%2C79&utm_source=chatgpt.com https://www.tsmh.org.tw/sites/tsmhcare/fee.html?utm_source=chatgpt.com https://www.paochien.com.tw/twuse/page?pageid=1100005&typeid=1000&utm_source=chatgpt.com https://wwwv.tsgh.ndmutsgh.edu.tw/unit/10071/17981
A5: Nurse call band | B5: https://store.directsupply.com/Product/replacement-wristband-transmitter-tl-4005-door-systems-11023710?quantity=1
A6: Japanese Market
A7: Korean Market | B7: https://www.jkgn.org/journal/view.php?number=619&utm_source=chatgpt.com
A8: Japanese Market | B8: https://www.mhlw.go.jp/toukei/saikin/hw/kaigo/service24/dl/gaikyo.pdf?utm_source=chatgpt.com
A9: Questions | B9: Financial | C9: Is the market too small? Should we expand to other countries? From what year?
C10: NPV too small?
C11: Warranty = 5% too small or not?
C12: R&D 2% is too small or not?
C13: Do we have to make the balance sheet & cashflow ?
C14: 400k Funding is enough or not?
C15: Should we include salary of C-Level?
C16: WACC 20% ?
B17: Validation | C17: What if we haven't gotten any KPI?
